{"code": "E05007893", "name": "Warndon Parish North", "type": "wd", "area": 249.69, "count": 8056, "parents": [{"code": "E07000237", "name": "Worcester", "type": "lad"}, {"code": "E12000005", "name": "West Midlands", "type": "rgn"}, {"code": "E92000001", "name": "England", "type": "ctry"}, {"code": "K04000001", "name": "England and Wales", "type": "ew"}], "bounds": [[-2.19575, 52.20011], [-2.1573, 52.21843]], "data": {"population": {"perc": {"2001": {"female": 49.46, "male": 50.54}, "2011": {"female": 50.5, "male": 49.5}, "change": {"female": 1.04, "male": -1.04}}, "perc_rank": {"2001": {"female": 7478, "male": 565}, "2011": {"female": 5581, "male": 2448}, "change": {"female": 511, "male": 7537}}, "value": {"2001": {"all": 5231, "female": 2587, "male": 2644}, "2011": {"all": 5517, "female": 2786, "male": 2731}, "change": {"all": 5.47, "female": 7.69, "male": 3.29}}, "value_rank": {"2001": {"all": 4207, "female": 4355, "male": 4057}, "2011": {"all": 4236, "female": 4277, "male": 4192}, "change": {"all": 3682, "female": 2692, "male": 4876}}, "value_rank_local": {"2011": {"all": -4, "female": -4, "male": -4}, "change": {"all": 6, "female": 3, "male": -8}}}, "age10yr": {"perc": {"2001": {"0-9": 18.47, "10-19": 8.52, "20-29": 17.99, "30-39": 30.0, "40-49": 12.31, "50-59": 7.89, "60-69": 3.01, "70plus": 1.81}, "2011": {"0-9": 15.1, "10-19": 12.2, "20-29": 12.33, "30-39": 17.53, "40-49": 20.88, "50-59": 11.24, "60-69": 6.74, "70plus": 3.99}, "change": {"0-9": -3.37, "10-19": 3.68, "20-29": -5.66, "30-39": -12.47, "40-49": 8.57, "50-59": 3.35, "60-69": 3.73, "70plus": 2.18}}, "perc_rank": {"2001": {"0-9": 87, "10-19": 7822, "20-29": 669, "30-39": 2, "40-49": 6391, "50-59": 7798, "60-69": 8025, "70plus": 8031}, "2011": {"0-9": 559, "10-19": 3415, "20-29": 2961, "30-39": 570, "40-49": 12, "50-59": 6322, "60-69": 7428, "70plus": 7949}, "change": {"0-9": 7778, "10-19": 84, "20-29": 8000, "30-39": 8055, "40-49": 5, "50-59": 120, "60-69": 1973, "70plus": 1954}}, "value": {"2001": {"0-9": 969, "10-19": 447, "20-29": 944, "30-39": 1574, "40-49": 646, "50-59": 414, "60-69": 158, "70plus": 95, "all": 5247}, "2011": {"0-9": 833, "10-19": 673, "20-29": 680, "30-39": 967, "40-49": 1152, "50-59": 620, "60-69": 372, "70plus": 220, "all": 5517}, "change": {"0-9": -14.04, "10-19": 50.56, "20-29": -27.97, "30-39": -38.56, "40-49": 78.33, "50-59": 49.76, "60-69": 135.44, "70plus": 131.58, "all": 5.15}}, "value_rank": {"2001": {"0-9": 2410, "10-19": 5715, "20-29": 2428, "30-39": 1670, "40-49": 4618, "50-59": 6490, "60-69": 7795, "70plus": 7994, "all": 4197}, "2011": {"0-9": 3015, "10-19": 4115, "20-29": 3732, "30-39": 2799, "40-49": 2752, "50-59": 4874, "60-69": 6754, "70plus": 7749, "all": 4236}, "change": {"0-9": 6411, "10-19": 229, "20-29": 7944, "30-39": 7723, "40-49": 141, "50-59": 181, "60-69": 55, "70plus": 43, "all": 3804}}, "perc_rank_local": {"2011": {"0-9": 2, "10-19": 7, "20-29": -6, "30-39": 2, "40-49": 1, "50-59": -5, "60-69": -2, "70plus": -1}, "change": {"0-9": -1, "10-19": 2, "20-29": -1, "30-39": -1, "40-49": 1, "50-59": 2, "60-69": 2, "70plus": 3}}}, "ethnicity": {"perc": {"2001": {"asian": 1.37, "black": 0.34, "mixed": 0.8, "other": 0.3, "white": 97.18}, "2011": {"asian": 3.35, "black": 0.47, "mixed": 1.31, "other": 0.2, "white": 94.67}, "change": {"asian": 1.98, "black": 0.13, "mixed": 0.51, "other": -0.1, "white": -2.51}}, "perc_rank": {"2001": {"asian": 2712, "black": 2889, "mixed": 3176, "other": 1966, "white": 5250}, "2011": {"asian": 2367, "black": 3613, "mixed": 3454, "other": 4008, "white": 5228}, "change": {"asian": 1953, "black": 4477, "mixed": 4033, "other": 7042, "white": 5215}}, "value": {"2001": {"all": 5246, "asian": 72, "black": 18, "mixed": 42, "other": 16, "white": 5098}, "2011": {"all": 5517, "asian": 185, "black": 26, "mixed": 72, "other": 11, "white": 5223}, "change": {"all": 5.17, "asian": 156.94, "black": 44.44, "mixed": 71.43, "other": -31.25, "white": 2.45}}, "value_rank": {"2001": {"all": 4195, "asian": 3052, "black": 3045, "mixed": 3461, "other": 2316, "white": 4041}, "2011": {"all": 4236, "asian": 2739, "black": 3712, "mixed": 3668, "other": 4037, "white": 4030}, "change": {"all": 3795, "asian": 2536, "black": 5445, "mixed": 4882, "other": 6666, "white": 3514}}, "perc_rank_local": {"2011": {"asian": -8, "black": 6, "mixed": -7, "other": -8, "white": -8}, "change": {"asian": 5, "black": 7, "mixed": -6, "other": -3, "white": -7}}}, "health": {"perc": {"2001": {"bad": 3.23, "fair": 14.22, "good": 82.55}, "2011": {"bad": 2.1, "fair": 7.32, "good": 90.57}, "change": {"bad": -1.13, "fair": -6.9, "good": 8.02}}, "perc_rank": {"2001": {"bad": 8024, "fair": 8021, "good": 20}, "2011": {"bad": 7953, "fair": 7942, "good": 94}, "change": {"bad": 97, "fair": 746, "good": 7971}}, "value": {"2001": {"all": 5231, "bad": 169, "fair": 744, "good": 4318}, "2011": {"all": 5517, "bad": 116, "fair": 404, "good": 4997}, "change": {"all": 5.47, "bad": -31.36, "fair": -45.7, "good": 15.72}}, "value_rank": {"2001": {"all": 4207, "bad": 7192, "fair": 6010, "good": 3337}, "2011": {"all": 4236, "bad": 6996, "fair": 6477, "good": 3719}, "change": {"all": 3682, "bad": 2475, "fair": 7442, "good": 6466}}, "perc_rank_local": {"2011": {"bad": -1, "fair": -1, "good": 1}, "change": {"bad": 1, "fair": 1, "good": -1}}}, "economic": {"perc": {"2001": {"employee": 76.64, "inactive": 14.25, "self-employed": 5.47, "student": 1.87, "unemployed": 1.77}, "2011": {"employee": 69.93, "inactive": 16.1, "self-employed": 8.24, "student": 2.99, "unemployed": 2.75}, "change": {"employee": -6.71, "inactive": 1.85, "self-employed": 2.77, "student": 1.12, "unemployed": 0.98}}, "perc_rank": {"2001": {"employee": 12, "inactive": 8034, "self-employed": 6630, "student": 5344, "unemployed": 6508}, "2011": {"employee": 33, "inactive": 8016, "self-employed": 5361, "student": 2297, "unemployed": 5384}, "change": {"employee": 7950, "inactive": 360, "self-employed": 682, "student": 1286, "unemployed": 3304}}, "value": {"2001": {"all": 3909, "employee": 2996, "inactive": 557, "self-employed": 214, "student": 73, "unemployed": 69}, "2011": {"all": 4150, "employee": 2902, "inactive": 668, "self-employed": 342, "student": 124, "unemployed": 114}, "change": {"all": 6.17, "employee": -3.14, "inactive": 19.93, "self-employed": 59.81, "student": 69.86, "unemployed": 65.22}}, "value_rank": {"2001": {"all": 4053, "employee": 2510, "inactive": 6979, "self-employed": 6179, "student": 4530, "unemployed": 5197}, "2011": {"all": 4093, "employee": 2927, "inactive": 6479, "self-employed": 5005, "student": 3525, "unemployed": 4721}, "change": {"all": 3847, "employee": 6899, "inactive": 444, "self-employed": 751, "student": 1630, "unemployed": 2067}}, "perc_rank_local": {"2011": {"employee": 1, "inactive": -1, "self-employed": 7, "student": -5, "unemployed": -5}, "change": {"employee": -3, "inactive": 1, "self-employed": 1, "student": 6, "unemployed": -7}}}, "travel": {"perc": {"2001": {"bicycle": 5.98, "bus": 2.47, "car_van": 76.43, "foot": 6.67, "home": 5.66, "moto": 2.33, "other": 0.06, "taxi": 0.12, "train_metro": 0.26}, "2011": {"bicycle": 2.72, "bus": 2.48, "car_van": 81.48, "foot": 6.51, "home": 4.24, "moto": 0.63, "other": 0.57, "taxi": 0.15, "train_metro": 1.22}, "change": {"bicycle": -3.26, "bus": 0.01, "car_van": 5.05, "foot": -0.16, "home": -1.42, "moto": -1.7, "other": 0.51, "taxi": 0.03, "train_metro": 0.96}}, "perc_rank": {"2001": {"bicycle": 531, "bus": 4640, "car_van": 549, "foot": 6503, "home": 6864, "moto": 175, "other": 6845, "taxi": 6092, "train_metro": 5721}, "2011": {"bicycle": 2352, "bus": 5110, "car_van": 514, "foot": 5561, "home": 4849, "moto": 4723, "other": 4176, "taxi": 6200, "train_metro": 5654}, "change": {"bicycle": 7860, "bus": 5170, "car_van": 4235, "foot": 3332, "home": 1323, "moto": 7971, "other": 1683, "taxi": 3486, "train_metro": 5279}}, "value": {"2001": {"all": 4930, "bicycle": 295, "bus": 122, "car_van": 3768, "foot": 329, "home": 279, "moto": 115, "other": 3, "taxi": 6, "train_metro": 13}, "2011": {"all": 3347, "bicycle": 91, "bus": 83, "car_van": 2727, "foot": 218, "home": 142, "moto": 21, "other": 19, "taxi": 5, "train_metro": 41}, "change": {"all": -32.11, "bicycle": -69.15, "bus": -31.97, "car_van": -27.63, "foot": -33.74, "home": -49.1, "moto": -81.74, "other": 533.33, "taxi": -16.67, "train_metro": 215.38}}, "value_rank": {"2001": {"all": 1102, "bicycle": 391, "bus": 2520, "car_van": 860, "foot": 2293, "home": 3199, "moto": 348, "other": 5298, "taxi": 3908, "train_metro": 3512}, "2011": {"all": 3156, "bicycle": 2435, "bus": 4175, "car_van": 1994, "foot": 4627, "home": 4243, "moto": 3702, "other": 3353, "taxi": 5100, "train_metro": 4816}, "change": {"all": 7128, "bicycle": 7775, "bus": 6671, "car_van": 6727, "foot": 7572, "home": 5940, "moto": 7693, "other": 1647, "taxi": 5571, "train_metro": 6036}}, "perc_rank_local": {"2011": {"bicycle": -2, "bus": -1, "car_van": 1, "foot": -1, "home": -8, "moto": -4, "other": 6, "taxi": -2, "train_metro": -4}, "change": {"bicycle": -1, "bus": -6, "car_van": 7, "foot": -6, "home": 2, "moto": -1, "other": 4, "taxi": -4, "train_metro": -6}}}, "tenure": {"perc": {"2001": {"owned": 90.7, "rent_free": 0.42, "rented_private": 7.47, "rented_social": 0.99, "shared_ownership": 0.42}, "2011": {"owned": 75.57, "rent_free": 0.4, "rented_private": 20.03, "rented_social": 3.86, "shared_ownership": 0.13}, "change": {"owned": -15.13, "rent_free": -0.02, "rented_private": 12.56, "rented_social": 2.87, "shared_ownership": -0.29}}, "perc_rank": {"2001": {"owned": 343, "rent_free": 7941, "rented_private": 4102, "rented_social": 7957, "shared_ownership": 4116}, "2011": {"owned": 2696, "rent_free": 7952, "rented_private": 1528, "rented_social": 7397, "shared_ownership": 7195}, "change": {"owned": 7924, "rent_free": 1221, "rented_private": 454, "rented_social": 208, "shared_ownership": 6596}}, "value": {"2001": {"all": 2129, "owned": 1931, "rent_free": 9, "rented_private": 159, "rented_social": 21, "shared_ownership": 9}, "2011": {"all": 2227, "owned": 1683, "rent_free": 9, "rented_private": 446, "rented_social": 86, "shared_ownership": 3}, "change": {"all": 4.6, "owned": -12.84, "rent_free": 0.0, "rented_private": 180.5, "rented_social": 309.52, "shared_ownership": -66.67}}, "value_rank": {"2001": {"all": 4310, "owned": 3117, "rent_free": 7690, "rented_private": 4094, "rented_social": 7853, "shared_ownership": 3921}, "2011": {"all": 4427, "owned": 3808, "rent_free": 7634, "rented_private": 2667, "rented_social": 6795, "shared_ownership": 6616}, "change": {"all": 4335, "owned": 7571, "rent_free": 1409, "rented_private": 843, "rented_social": 54, "shared_ownership": 7359}}, "perc_rank_local": {"2011": {"owned": 7, "rent_free": -1, "rented_private": 3, "rented_social": -3, "shared_ownership": -1}, "change": {"owned": -2, "rent_free": 3, "rented_private": 3, "rented_social": 2, "shared_ownership": -4}}}, "density": {"value": {"2001": {"all": 20.95}, "2011": {"all": 22.1}, "change": {"all": 5.49}}, "value_rank": {"2001": {"all": 3126}, "2011": {"all": 3178}, "change": {"all": 3679}}, "value_rank_local": {"2011": {"all": -3}, "change": {"all": 6}}}, "agemed": {"value": {"2001": {"all": 29.0}, "2011": {"all": 33.0}, "change": {"all": 13.79}}, "value_rank": {"2001": {"all": 7969}, "2011": {"all": 7337}, "change": {"all": 68}}, "value_rank_local": {"2011": {"all": -2}, "change": {"all": 1}}}}, "Priorities": [{"label": "age10yr_perc_2011_40-49", "value": 1, "sqr": 1, "sqrt": 1.0, "abVal": 20.88}, {"label": "age10yr_perc_2011_70plus", "value": -1, "sqr": 1, "sqrt": 1.0, "abVal": 3.99}, {"label": "age10yr_perc_change_0-9", "value": -1, "sqr": 1, "sqrt": 1.0, "abVal": -3.37}, {"label": "age10yr_perc_change_20-29", "value": -1, "sqr": 1, "sqrt": 1.0, "abVal": -5.66}, {"label": "age10yr_perc_change_30-39", "value": -1, "sqr": 1, "sqrt": 1.0, "abVal": -12.47}, {"label": "age10yr_perc_change_40-49", "value": 1, "sqr": 1, "sqrt": 1.0, "abVal": 8.57}, {"label": "health_perc_2011_bad", "value": -1, "sqr": 1, "sqrt": 1.0, "abVal": 2.1}, {"label": "health_perc_2011_fair", "value": -1, "sqr": 1, "sqrt": 1.0, "abVal": 7.32}, {"label": "health_perc_2011_good", "value": 1, "sqr": 1, "sqrt": 1.0, "abVal": 90.57}, {"label": "health_perc_change_bad", "value": 1, "sqr": 1, "sqrt": 1.0, "abVal": -1.13}, {"label": "health_perc_change_fair", "value": 1, "sqr": 1, "sqrt": 1.0, "abVal": -6.9}, {"label": "health_perc_change_good", "value": -1, "sqr": 1, "sqrt": 1.0, "abVal": 8.02}, {"label": "economic_perc_2011_employee", "value": 1, "sqr": 1, "sqrt": 1.0, "abVal": 69.93}, {"label": "economic_perc_2011_inactive", "value": -1, "sqr": 1, "sqrt": 1.0, "abVal": 16.1}, {"label": "economic_perc_change_inactive", "value": 1, "sqr": 1, "sqrt": 1.0, "abVal": 1.85}, {"label": "economic_perc_change_self-employed", "value": 1, "sqr": 1, "sqrt": 1.0, "abVal": 2.77}, {"label": "travel_perc_2011_bus", "value": -1, "sqr": 1, "sqrt": 1.0, "abVal": 2.48}, {"label": "travel_perc_2011_car_van", "value": 1, "sqr": 1, "sqrt": 1.0, "abVal": 81.48}, {"label": "travel_perc_2011_foot", "value": -1, "sqr": 1, "sqrt": 1.0, "abVal": 6.51}, {"label": "travel_perc_change_bicycle", "value": -1, "sqr": 1, "sqrt": 1.0, "abVal": -3.26}, {"label": "travel_perc_change_moto", "value": -1, "sqr": 1, "sqrt": 1.0, "abVal": -1.7}, {"label": "tenure_perc_2011_rent_free", "value": -1, "sqr": 1, "sqrt": 1.0, "abVal": 0.4}, {"label": "tenure_perc_2011_shared_ownership", "value": -1, "sqr": 1, "sqrt": 1.0, "abVal": 0.13}, {"label": "agemed_value_change_all", "value": 1, "sqr": 1, "sqrt": 1.0, "abVal": 13.79}, {"label": "age10yr_perc_2011_0-9", "value": 2, "sqr": 4, "sqrt": 2.0, "abVal": 15.1}, {"label": "age10yr_perc_2011_30-39", "value": 2, "sqr": 4, "sqrt": 2.0, "abVal": 17.53}, {"label": "age10yr_perc_2011_60-69", "value": -2, "sqr": 4, "sqrt": 2.0, "abVal": 6.74}, {"label": "age10yr_perc_change_10-19", "value": 2, "sqr": 4, "sqrt": 2.0, "abVal": 3.68}, {"label": "age10yr_perc_change_50-59", "value": 2, "sqr": 4, "sqrt": 2.0, "abVal": 3.35}, {"label": "age10yr_perc_change_60-69", "value": 2, "sqr": 4, "sqrt": 2.0, "abVal": 3.73}, {"label": "travel_perc_2011_bicycle", "value": -2, "sqr": 4, "sqrt": 2.0, "abVal": 2.72}, {"label": "travel_perc_2011_taxi", "value": -2, "sqr": 4, "sqrt": 2.0, "abVal": 0.15}, {"label": "travel_perc_change_home", "value": 2, "sqr": 4, "sqrt": 2.0, "abVal": -1.42}, {"label": "tenure_perc_change_owned", "value": -2, "sqr": 4, "sqrt": 2.0, "abVal": -15.13}, {"label": "tenure_perc_change_rented_social", "value": 2, "sqr": 4, "sqrt": 2.0, "abVal": 2.87}, {"label": "agemed_value_2011_all", "value": -2, "sqr": 4, "sqrt": 2.0, "abVal": 33.0}, {"label": "population_value_change_female", "value": 3, "sqr": 9, "sqrt": 3.0, "abVal": 7.69}, {"label": "age10yr_perc_change_70plus", "value": 3, "sqr": 9, "sqrt": 3.0, "abVal": 2.18}, {"label": "ethnicity_perc_change_other", "value": -3, "sqr": 9, "sqrt": 3.0, "abVal": -0.1}, {"label": "economic_perc_change_employee", "value": -3, "sqr": 9, "sqrt": 3.0, "abVal": -6.71}, {"label": "tenure_perc_2011_rented_private", "value": 3, "sqr": 9, "sqrt": 3.0, "abVal": 20.03}, {"label": "tenure_perc_2011_rented_social", "value": -3, "sqr": 9, "sqrt": 3.0, "abVal": 3.86}, {"label": "tenure_perc_change_rent_free", "value": 3, "sqr": 9, "sqrt": 3.0, "abVal": -0.02}, {"label": "tenure_perc_change_rented_private", "value": 3, "sqr": 9, "sqrt": 3.0, "abVal": 12.56}, {"label": "density_value_2011_all", "value": -3, "sqr": 9, "sqrt": 3.0, "abVal": 22.1}, {"label": "population_value_2011_all", "value": -4, "sqr": 16, "sqrt": 4.0, "abVal": 5517}, {"label": "population_value_2011_female", "value": -4, "sqr": 16, "sqrt": 4.0, "abVal": 2786}, {"label": "population_value_2011_male", "value": -4, "sqr": 16, "sqrt": 4.0, "abVal": 2731}, {"label": "travel_perc_2011_moto", "value": -4, "sqr": 16, "sqrt": 4.0, "abVal": 0.63}, {"label": "travel_perc_2011_train_metro", "value": -4, "sqr": 16, "sqrt": 4.0, "abVal": 1.22}, {"label": "travel_perc_change_other", "value": 4, "sqr": 16, "sqrt": 4.0, "abVal": 0.51}, {"label": "travel_perc_change_taxi", "value": -4, "sqr": 16, "sqrt": 4.0, "abVal": 0.03}, {"label": "tenure_perc_change_shared_ownership", "value": -4, "sqr": 16, "sqrt": 4.0, "abVal": -0.29}, {"label": "age10yr_perc_2011_50-59", "value": -5, "sqr": 25, "sqrt": 5.0, "abVal": 11.24}, {"label": "ethnicity_perc_change_asian", "value": 5, "sqr": 25, "sqrt": 5.0, "abVal": 1.98}, {"label": "economic_perc_2011_student", "value": -5, "sqr": 25, "sqrt": 5.0, "abVal": 2.99}, {"label": "economic_perc_2011_unemployed", "value": -5, "sqr": 25, "sqrt": 5.0, "abVal": 2.75}, {"label": "population_value_change_all", "value": 6, "sqr": 36, "sqrt": 6.0, "abVal": 5.47}, {"label": "age10yr_perc_2011_20-29", "value": -6, "sqr": 36, "sqrt": 6.0, "abVal": 12.33}, {"label": "ethnicity_perc_2011_black", "value": 6, "sqr": 36, "sqrt": 6.0, "abVal": 0.47}, {"label": "ethnicity_perc_change_mixed", "value": -6, "sqr": 36, "sqrt": 6.0, "abVal": 0.51}, {"label": "economic_perc_change_student", "value": 6, "sqr": 36, "sqrt": 6.0, "abVal": 1.12}, {"label": "travel_perc_2011_other", "value": 6, "sqr": 36, "sqrt": 6.0, "abVal": 0.57}, {"label": "travel_perc_change_bus", "value": -6, "sqr": 36, "sqrt": 6.0, "abVal": 0.01}, {"label": "travel_perc_change_foot", "value": -6, "sqr": 36, "sqrt": 6.0, "abVal": -0.16}, {"label": "travel_perc_change_train_metro", "value": -6, "sqr": 36, "sqrt": 6.0, "abVal": 0.96}, {"label": "density_value_change_all", "value": 6, "sqr": 36, "sqrt": 6.0, "abVal": 5.49}, {"label": "age10yr_perc_2011_10-19", "value": 7, "sqr": 49, "sqrt": 7.0, "abVal": 12.2}, {"label": "ethnicity_perc_2011_mixed", "value": -7, "sqr": 49, "sqrt": 7.0, "abVal": 1.31}, {"label": "ethnicity_perc_change_black", "value": 7, "sqr": 49, "sqrt": 7.0, "abVal": 0.13}, {"label": "ethnicity_perc_change_white", "value": -7, "sqr": 49, "sqrt": 7.0, "abVal": -2.51}, {"label": "economic_perc_2011_self-employed", "value": 7, "sqr": 49, "sqrt": 7.0, "abVal": 8.24}, {"label": "economic_perc_change_unemployed", "value": -7, "sqr": 49, "sqrt": 7.0, "abVal": 0.98}, {"label": "travel_perc_change_car_van", "value": 7, "sqr": 49, "sqrt": 7.0, "abVal": 5.05}, {"label": "tenure_perc_2011_owned", "value": 7, "sqr": 49, "sqrt": 7.0, "abVal": 75.57}, {"label": "population_value_change_male", "value": -8, "sqr": 64, "sqrt": 8.0, "abVal": 3.29}, {"label": "ethnicity_perc_2011_asian", "value": -8, "sqr": 64, "sqrt": 8.0, "abVal": 3.35}, {"label": "ethnicity_perc_2011_other", "value": -8, "sqr": 64, "sqrt": 8.0, "abVal": 0.2}, {"label": "ethnicity_perc_2011_white", "value": -8, "sqr": 64, "sqrt": 8.0, "abVal": 94.67}, {"label": "travel_perc_2011_home", "value": -8, "sqr": 64, "sqrt": 8.0, "abVal": 4.24}]}