{"code": "E07000032", "name": "Amber Valley", "type": "lad", "area": 26538.48, "count": 336, "parents": [{"code": "E12000004", "name": "East Midlands", "type": "rgn"}, {"code": "E92000001", "name": "England", "type": "ctry"}, {"code": "K04000001", "name": "England and Wales", "type": "ew"}], "bounds": [[-1.6101, 52.92419], [-1.30745, 53.13395]], "data": {"population": {"perc": {"2001": {"female": 51.0, "male": 49.0}, "2011": {"female": 50.79, "male": 49.21}, "change": {"female": -0.21, "male": 0.21}}, "perc_rank": {"2001": {"female": 217, "male": 119}, "2011": {"female": 194, "male": 139}, "change": {"female": 132, "male": 202}}, "value": {"2001": {"all": 116471, "female": 59400, "male": 57071}, "2011": {"all": 122309, "female": 62117, "male": 60192}, "change": {"all": 5.01, "female": 4.57, "male": 5.47}}, "value_rank": {"2001": {"all": 185, "female": 186, "male": 183}, "2011": {"all": 187, "female": 187, "male": 185}, "change": {"all": 234, "female": 222, "male": 235}}, "value_rank_local": {"2011": {"all": 8, "female": 8, "male": 8}, "change": {"all": -14, "female": -10, "male": -14}}}, "age10yr": {"perc": {"2001": {"0-9": 11.85, "10-19": 11.95, "20-29": 10.48, "30-39": 15.51, "40-49": 13.72, "50-59": 14.59, "60-69": 9.69, "70plus": 12.22}, "2011": {"0-9": 10.46, "10-19": 11.86, "20-29": 10.36, "30-39": 11.96, "40-49": 15.76, "50-59": 13.47, "60-69": 13.41, "70plus": 12.72}, "change": {"0-9": -1.39, "10-19": -0.09, "20-29": -0.12, "30-39": -3.55, "40-49": 2.04, "50-59": -1.12, "60-69": 3.72, "70plus": 0.5}}, "perc_rank": {"2001": {"0-9": 211, "10-19": 271, "20-29": 218, "30-39": 131, "40-49": 138, "50-59": 51, "60-69": 142, "70plus": 119}, "2011": {"0-9": 262, "10-19": 219, "20-29": 241, "30-39": 195, "40-49": 63, "50-59": 71, "60-69": 73, "70plus": 141}, "change": {"0-9": 300, "10-19": 69, "20-29": 259, "30-39": 264, "40-49": 41, "50-59": 272, "60-69": 17, "70plus": 176}}, "value": {"2001": {"0-9": 13798, "10-19": 13918, "20-29": 12204, "30-39": 18068, "40-49": 15981, "50-59": 16996, "60-69": 11282, "70plus": 14237, "all": 116484}, "2011": {"0-9": 12791, "10-19": 14507, "20-29": 12672, "30-39": 14629, "40-49": 19282, "50-59": 16470, "60-69": 16398, "70plus": 15560, "all": 122309}, "change": {"0-9": -7.3, "10-19": 4.23, "20-29": 3.83, "30-39": -19.03, "40-49": 20.66, "50-59": -3.09, "60-69": 45.35, "70plus": 9.29, "all": 5.0}}, "value_rank": {"2001": {"0-9": 182, "10-19": 195, "20-29": 188, "30-39": 169, "40-49": 184, "50-59": 154, "60-69": 182, "70plus": 179, "all": 185}, "2011": {"0-9": 199, "10-19": 196, "20-29": 200, "30-39": 186, "40-49": 164, "50-59": 171, "60-69": 143, "70plus": 184, "all": 187}, "change": {"0-9": 287, "10-19": 131, "20-29": 281, "30-39": 244, "40-49": 105, "50-59": 276, "60-69": 24, "70plus": 192, "all": 236}}, "perc_rank_local": {"2011": {"0-9": -10, "10-19": -13, "20-29": -15, "30-39": -19, "40-49": 15, "50-59": 14, "60-69": 8, "70plus": 18}, "change": {"0-9": -6, "10-19": 10, "20-29": -12, "30-39": -17, "40-49": 8, "50-59": -10, "60-69": 5, "70plus": -16}}}, "ethnicity": {"perc": {"2001": {"asian": 0.38, "black": 0.08, "mixed": 0.41, "other": 0.05, "white": 99.08}, "2011": {"asian": 0.76, "black": 0.21, "mixed": 0.8, "other": 0.1, "white": 98.13}, "change": {"asian": 0.38, "black": 0.13, "mixed": 0.39, "other": 0.05, "white": -0.95}}, "perc_rank": {"2001": {"asian": 306, "black": 303, "mixed": 288, "other": 322, "white": 24}, "2011": {"asian": 306, "black": 279, "mixed": 274, "other": 301, "white": 36}, "change": {"asian": 291, "black": 238, "mixed": 251, "other": 216, "white": 57}}, "value": {"2001": {"all": 116476, "asian": 437, "black": 96, "mixed": 483, "other": 58, "white": 115402}, "2011": {"all": 122309, "asian": 929, "black": 253, "mixed": 980, "other": 124, "white": 120023}, "change": {"all": 5.01, "asian": 112.59, "black": 163.54, "mixed": 102.9, "other": 113.79, "white": 4.0}}, "value_rank": {"2001": {"all": 185, "asian": 293, "black": 294, "mixed": 269, "other": 303, "white": 174}, "2011": {"all": 187, "asian": 286, "black": 274, "mixed": 258, "other": 284, "white": 165}, "change": {"all": 234, "asian": 126, "black": 88, "mixed": 97, "other": 131, "white": 128}}, "perc_rank_local": {"2011": {"asian": -4, "black": -5, "mixed": -7, "other": -6, "white": 6}, "change": {"asian": -10, "black": -13, "mixed": -13, "other": -18, "white": 8}}}, "health": {"perc": {"2001": {"bad": 10.06, "fair": 23.91, "good": 66.03}, "2011": {"bad": 6.01, "fair": 14.99, "good": 79.0}, "change": {"bad": -4.05, "fair": -8.92, "good": 12.97}}, "perc_rank": {"2001": {"bad": 93, "fair": 50, "good": 259}, "2011": {"bad": 106, "fair": 64, "good": 254}, "change": {"bad": 258, "fair": 166, "good": 83}}, "value": {"2001": {"all": 116471, "bad": 11718, "fair": 27852, "good": 76901}, "2011": {"all": 122309, "bad": 7352, "fair": 18336, "good": 96621}, "change": {"all": 5.01, "bad": -37.26, "fair": -34.17, "good": 25.64}}, "value_rank": {"2001": {"all": 185, "bad": 147, "fair": 160, "good": 200}, "2011": {"all": 187, "bad": 152, "fair": 150, "good": 202}, "change": {"all": 234, "bad": 250, "fair": 99, "good": 162}}, "perc_rank_local": {"2011": {"bad": 11, "fair": 10, "good": -10}, "change": {"bad": -8, "fair": 16, "good": 13}}}, "economic": {"perc": {"2001": {"employee": 55.58, "inactive": 31.95, "self-employed": 7.74, "student": 1.7, "unemployed": 3.04}, "2011": {"employee": 54.77, "inactive": 30.12, "self-employed": 9.04, "student": 2.2, "unemployed": 3.87}, "change": {"employee": -0.81, "inactive": -1.83, "self-employed": 1.3, "student": 0.5, "unemployed": 0.83}}, "perc_rank": {"2001": {"employee": 98, "inactive": 177, "self-employed": 220, "student": 313, "unemployed": 152}, "2011": {"employee": 103, "inactive": 154, "self-employed": 217, "student": 311, "unemployed": 167}, "change": {"employee": 210, "inactive": 87, "self-employed": 149, "student": 190, "unemployed": 201}}, "value": {"2001": {"all": 84332, "employee": 46869, "inactive": 26942, "self-employed": 6524, "student": 1436, "unemployed": 2561}, "2011": {"all": 90558, "employee": 49603, "inactive": 27278, "self-employed": 8183, "student": 1991, "unemployed": 3503}, "change": {"all": 7.38, "employee": 5.83, "inactive": 1.25, "self-employed": 25.43, "student": 38.65, "unemployed": 36.78}}, "value_rank": {"2001": {"all": 181, "employee": 165, "inactive": 177, "self-employed": 216, "student": 243, "unemployed": 157}, "2011": {"all": 183, "employee": 170, "inactive": 170, "self-employed": 211, "student": 236, "unemployed": 167}, "change": {"all": 184, "employee": 213, "inactive": 116, "self-employed": 151, "student": 151, "unemployed": 226}}, "perc_rank_local": {"2011": {"employee": -20, "inactive": 20, "self-employed": -18, "student": -6, "unemployed": 19}, "change": {"employee": -19, "inactive": 20, "self-employed": 7, "student": 20, "unemployed": 17}}}, "travel": {"perc": {"2001": {"bicycle": 1.74, "bus": 4.61, "car_van": 70.55, "foot": 11.34, "home": 9.67, "moto": 1.3, "other": 0.26, "taxi": 0.34, "train_metro": 0.2}, "2011": {"bicycle": 1.36, "bus": 4.06, "car_van": 76.78, "foot": 9.67, "home": 5.09, "moto": 0.98, "other": 0.43, "taxi": 0.33, "train_metro": 1.29}, "change": {"bicycle": -0.38, "bus": -0.55, "car_van": 6.23, "foot": -1.67, "home": -4.58, "moto": -0.32, "other": 0.17, "taxi": -0.01, "train_metro": 1.09}}, "perc_rank": {"2001": {"bicycle": 234, "bus": 158, "car_van": 61, "foot": 120, "home": 195, "moto": 69, "other": 256, "taxi": 225, "train_metro": 321}, "2011": {"bicycle": 260, "bus": 181, "car_van": 36, "foot": 191, "home": 188, "moto": 76, "other": 325, "taxi": 204, "train_metro": 267}, "change": {"bicycle": 197, "bus": 205, "car_van": 89, "foot": 251, "home": 146, "moto": 220, "other": 251, "taxi": 130, "train_metro": 219}}, "value": {"2001": {"all": 49164, "bicycle": 853, "bus": 2267, "car_van": 34685, "foot": 5575, "home": 4756, "moto": 637, "other": 127, "taxi": 165, "train_metro": 99}, "2011": {"all": 59381, "bicycle": 808, "bus": 2412, "car_van": 45593, "foot": 5744, "home": 3024, "moto": 584, "other": 256, "taxi": 193, "train_metro": 767}, "change": {"all": 20.78, "bicycle": -5.28, "bus": 6.4, "car_van": 31.45, "foot": 3.03, "home": -36.42, "moto": -8.32, "other": 101.57, "taxi": 16.97, "train_metro": 674.75}}, "value_rank": {"2001": {"all": 187, "bicycle": 246, "bus": 166, "car_van": 159, "foot": 172, "home": 211, "moto": 140, "other": 260, "taxi": 229, "train_metro": 297}, "2011": {"all": 180, "bicycle": 254, "bus": 180, "car_van": 131, "foot": 202, "home": 214, "moto": 128, "other": 265, "taxi": 211, "train_metro": 254}, "change": {"all": 164, "bicycle": 215, "bus": 186, "car_van": 125, "foot": 302, "home": 174, "moto": 154, "other": 181, "taxi": 132, "train_metro": 45}}, "perc_rank_local": {"2011": {"bicycle": -7, "bus": 19, "car_van": 12, "foot": -20, "home": -20, "moto": 4, "other": -4, "taxi": 17, "train_metro": -17}, "change": {"bicycle": 13, "bus": -17, "car_van": -16, "foot": -17, "home": 12, "moto": -20, "other": -15, "taxi": 14, "train_metro": 20}}}, "tenure": {"perc": {"2001": {"owned": 77.14, "rent_free": 2.35, "rented_private": 6.8, "rented_social": 13.26, "shared_ownership": 0.45}, "2011": {"owned": 74.1, "rent_free": 1.37, "rented_private": 11.79, "rented_social": 12.33, "shared_ownership": 0.41}, "change": {"owned": -3.04, "rent_free": -0.98, "rented_private": 4.99, "rented_social": -0.93, "shared_ownership": -0.04}}, "perc_rank": {"2001": {"owned": 61, "rent_free": 93, "rented_private": 248, "rented_social": 226, "shared_ownership": 217}, "2011": {"owned": 41, "rent_free": 138, "rented_private": 268, "rented_social": 244, "shared_ownership": 269}, "change": {"owned": 88, "rent_free": 275, "rented_private": 225, "rented_social": 185, "shared_ownership": 250}}, "value": {"2001": {"all": 49435, "owned": 38133, "rent_free": 1162, "rented_private": 3362, "rented_social": 6557, "shared_ownership": 221}, "2011": {"all": 52596, "owned": 38974, "rent_free": 722, "rented_private": 6200, "rented_social": 6484, "shared_ownership": 216}, "change": {"all": 6.39, "owned": 2.21, "rent_free": -37.87, "rented_private": 84.41, "rented_social": -1.11, "shared_ownership": -2.26}}, "value_rank": {"2001": {"all": 177, "owned": 155, "rent_free": 129, "rented_private": 225, "rented_social": 200, "shared_ownership": 215}, "2011": {"all": 182, "owned": 151, "rent_free": 168, "rented_private": 226, "rented_social": 208, "shared_ownership": 265}, "change": {"all": 190, "owned": 114, "rent_free": 284, "rented_private": 169, "rented_social": 214, "shared_ownership": 253}}, "perc_rank_local": {"2011": {"owned": 10, "rent_free": 18, "rented_private": -8, "rented_social": -17, "shared_ownership": -9}, "change": {"owned": 15, "rent_free": -10, "rented_private": -12, "rented_social": 16, "shared_ownership": -9}}}, "density": {"value": {"2001": {"all": 4.39}, "2011": {"all": 4.61}, "change": {"all": 5.01}}, "value_rank": {"2001": {"all": 196}, "2011": {"all": 196}, "change": {"all": 231}}, "value_rank_local": {"2011": {"all": 18}, "change": {"all": -14}}}, "agemed": {"value": {"2001": {"all": 39.0}, "2011": {"all": 40.0}, "change": {"all": 2.56}}, "value_rank": {"2001": {"all": 67}, "2011": {"all": 86}, "change": {"all": 181}}, "value_rank_local": {"2011": {"all": 8}, "change": {"all": -15}}}}, "Priorities": [{"label": "ethnicity_perc_2011_asian", "value": -4, "sqr": 16, "sqrt": 4.0, "abVal": 0.76}, {"label": "travel_perc_2011_moto", "value": 4, "sqr": 16, "sqrt": 4.0, "abVal": 0.98}, {"label": "travel_perc_2011_other", "value": -4, "sqr": 16, "sqrt": 4.0, "abVal": 0.43}, {"label": "age10yr_perc_change_60-69", "value": 5, "sqr": 25, "sqrt": 5.0, "abVal": 3.72}, {"label": "ethnicity_perc_2011_black", "value": -5, "sqr": 25, "sqrt": 5.0, "abVal": 0.21}, {"label": "age10yr_perc_change_0-9", "value": -6, "sqr": 36, "sqrt": 6.0, "abVal": -1.39}, {"label": "ethnicity_perc_2011_other", "value": -6, "sqr": 36, "sqrt": 6.0, "abVal": 0.1}, {"label": "ethnicity_perc_2011_white", "value": 6, "sqr": 36, "sqrt": 6.0, "abVal": 98.13}, {"label": "economic_perc_2011_student", "value": -6, "sqr": 36, "sqrt": 6.0, "abVal": 2.2}, {"label": "ethnicity_perc_2011_mixed", "value": -7, "sqr": 49, "sqrt": 7.0, "abVal": 0.8}, {"label": "economic_perc_change_self-employed", "value": 7, "sqr": 49, "sqrt": 7.0, "abVal": 1.3}, {"label": "travel_perc_2011_bicycle", "value": -7, "sqr": 49, "sqrt": 7.0, "abVal": 1.36}, {"label": "population_value_2011_all", "value": 8, "sqr": 64, "sqrt": 8.0, "abVal": 122309}, {"label": "population_value_2011_female", "value": 8, "sqr": 64, "sqrt": 8.0, "abVal": 62117}, {"label": "population_value_2011_male", "value": 8, "sqr": 64, "sqrt": 8.0, "abVal": 60192}, {"label": "age10yr_perc_2011_60-69", "value": 8, "sqr": 64, "sqrt": 8.0, "abVal": 13.41}, {"label": "age10yr_perc_change_40-49", "value": 8, "sqr": 64, "sqrt": 8.0, "abVal": 2.04}, {"label": "ethnicity_perc_change_white", "value": 8, "sqr": 64, "sqrt": 8.0, "abVal": -0.95}, {"label": "health_perc_change_bad", "value": -8, "sqr": 64, "sqrt": 8.0, "abVal": -4.05}, {"label": "tenure_perc_2011_rented_private", "value": -8, "sqr": 64, "sqrt": 8.0, "abVal": 11.79}, {"label": "agemed_value_2011_all", "value": 8, "sqr": 64, "sqrt": 8.0, "abVal": 40.0}, {"label": "tenure_perc_2011_shared_ownership", "value": -9, "sqr": 81, "sqrt": 9.0, "abVal": 0.41}, {"label": "tenure_perc_change_shared_ownership", "value": -9, "sqr": 81, "sqrt": 9.0, "abVal": -0.04}, {"label": "population_value_change_female", "value": -10, "sqr": 100, "sqrt": 10.0, "abVal": 4.57}, {"label": "age10yr_perc_2011_0-9", "value": -10, "sqr": 100, "sqrt": 10.0, "abVal": 10.46}, {"label": "age10yr_perc_change_10-19", "value": 10, "sqr": 100, "sqrt": 10.0, "abVal": -0.09}, {"label": "age10yr_perc_change_50-59", "value": -10, "sqr": 100, "sqrt": 10.0, "abVal": -1.12}, {"label": "ethnicity_perc_change_asian", "value": -10, "sqr": 100, "sqrt": 10.0, "abVal": 0.38}, {"label": "health_perc_2011_fair", "value": 10, "sqr": 100, "sqrt": 10.0, "abVal": 14.99}, {"label": "health_perc_2011_good", "value": -10, "sqr": 100, "sqrt": 10.0, "abVal": 79.0}, {"label": "tenure_perc_2011_owned", "value": 10, "sqr": 100, "sqrt": 10.0, "abVal": 74.1}, {"label": "tenure_perc_change_rent_free", "value": -10, "sqr": 100, "sqrt": 10.0, "abVal": -0.98}, {"label": "health_perc_2011_bad", "value": 11, "sqr": 121, "sqrt": 11.0, "abVal": 6.01}, {"label": "age10yr_perc_change_20-29", "value": -12, "sqr": 144, "sqrt": 12.0, "abVal": -0.12}, {"label": "travel_perc_2011_car_van", "value": 12, "sqr": 144, "sqrt": 12.0, "abVal": 76.78}, {"label": "travel_perc_change_home", "value": 12, "sqr": 144, "sqrt": 12.0, "abVal": -4.58}, {"label": "tenure_perc_change_rented_private", "value": -12, "sqr": 144, "sqrt": 12.0, "abVal": 4.99}, {"label": "age10yr_perc_2011_10-19", "value": -13, "sqr": 169, "sqrt": 13.0, "abVal": 11.86}, {"label": "ethnicity_perc_change_black", "value": -13, "sqr": 169, "sqrt": 13.0, "abVal": 0.13}, {"label": "ethnicity_perc_change_mixed", "value": -13, "sqr": 169, "sqrt": 13.0, "abVal": 0.39}, {"label": "health_perc_change_good", "value": 13, "sqr": 169, "sqrt": 13.0, "abVal": 12.97}, {"label": "travel_perc_change_bicycle", "value": 13, "sqr": 169, "sqrt": 13.0, "abVal": -0.38}, {"label": "population_value_change_all", "value": -14, "sqr": 196, "sqrt": 14.0, "abVal": 5.01}, {"label": "population_value_change_male", "value": -14, "sqr": 196, "sqrt": 14.0, "abVal": 5.47}, {"label": "age10yr_perc_2011_50-59", "value": 14, "sqr": 196, "sqrt": 14.0, "abVal": 13.47}, {"label": "travel_perc_change_taxi", "value": 14, "sqr": 196, "sqrt": 14.0, "abVal": -0.01}, {"label": "density_value_change_all", "value": -14, "sqr": 196, "sqrt": 14.0, "abVal": 5.01}, {"label": "age10yr_perc_2011_20-29", "value": -15, "sqr": 225, "sqrt": 15.0, "abVal": 10.36}, {"label": "age10yr_perc_2011_40-49", "value": 15, "sqr": 225, "sqrt": 15.0, "abVal": 15.76}, {"label": "travel_perc_change_other", "value": -15, "sqr": 225, "sqrt": 15.0, "abVal": 0.17}, {"label": "tenure_perc_change_owned", "value": 15, "sqr": 225, "sqrt": 15.0, "abVal": -3.04}, {"label": "agemed_value_change_all", "value": -15, "sqr": 225, "sqrt": 15.0, "abVal": 2.56}, {"label": "age10yr_perc_change_70plus", "value": -16, "sqr": 256, "sqrt": 16.0, "abVal": 0.5}, {"label": "health_perc_change_fair", "value": 16, "sqr": 256, "sqrt": 16.0, "abVal": -8.92}, {"label": "travel_perc_change_car_van", "value": -16, "sqr": 256, "sqrt": 16.0, "abVal": 6.23}, {"label": "tenure_perc_change_rented_social", "value": 16, "sqr": 256, "sqrt": 16.0, "abVal": -0.93}, {"label": "age10yr_perc_change_30-39", "value": -17, "sqr": 289, "sqrt": 17.0, "abVal": -3.55}, {"label": "economic_perc_change_unemployed", "value": 17, "sqr": 289, "sqrt": 17.0, "abVal": 0.83}, {"label": "travel_perc_2011_taxi", "value": 17, "sqr": 289, "sqrt": 17.0, "abVal": 0.33}, {"label": "travel_perc_2011_train_metro", "value": -17, "sqr": 289, "sqrt": 17.0, "abVal": 1.29}, {"label": "travel_perc_change_bus", "value": -17, "sqr": 289, "sqrt": 17.0, "abVal": -0.55}, {"label": "travel_perc_change_foot", "value": -17, "sqr": 289, "sqrt": 17.0, "abVal": -1.67}, {"label": "tenure_perc_2011_rented_social", "value": -17, "sqr": 289, "sqrt": 17.0, "abVal": 12.33}, {"label": "age10yr_perc_2011_70plus", "value": 18, "sqr": 324, "sqrt": 18.0, "abVal": 12.72}, {"label": "ethnicity_perc_change_other", "value": -18, "sqr": 324, "sqrt": 18.0, "abVal": 0.05}, {"label": "economic_perc_2011_self-employed", "value": -18, "sqr": 324, "sqrt": 18.0, "abVal": 9.04}, {"label": "tenure_perc_2011_rent_free", "value": 18, "sqr": 324, "sqrt": 18.0, "abVal": 1.37}, {"label": "density_value_2011_all", "value": 18, "sqr": 324, "sqrt": 18.0, "abVal": 4.61}, {"label": "age10yr_perc_2011_30-39", "value": -19, "sqr": 361, "sqrt": 19.0, "abVal": 11.96}, {"label": "economic_perc_2011_unemployed", "value": 19, "sqr": 361, "sqrt": 19.0, "abVal": 3.87}, {"label": "economic_perc_change_employee", "value": -19, "sqr": 361, "sqrt": 19.0, "abVal": -0.81}, {"label": "travel_perc_2011_bus", "value": 19, "sqr": 361, "sqrt": 19.0, "abVal": 4.06}, {"label": "economic_perc_2011_employee", "value": -20, "sqr": 400, "sqrt": 20.0, "abVal": 54.77}, {"label": "economic_perc_2011_inactive", "value": 20, "sqr": 400, "sqrt": 20.0, "abVal": 30.12}, {"label": "economic_perc_change_inactive", "value": 20, "sqr": 400, "sqrt": 20.0, "abVal": -1.83}, {"label": "economic_perc_change_student", "value": 20, "sqr": 400, "sqrt": 20.0, "abVal": 0.5}, {"label": "travel_perc_2011_foot", "value": -20, "sqr": 400, "sqrt": 20.0, "abVal": 9.67}, {"label": "travel_perc_2011_home", "value": -20, "sqr": 400, "sqrt": 20.0, "abVal": 5.09}, {"label": "travel_perc_change_moto", "value": -20, "sqr": 400, "sqrt": 20.0, "abVal": -0.32}, {"label": "travel_perc_change_train_metro", "value": 20, "sqr": 400, "sqrt": 20.0, "abVal": 1.09}]}